dolphin_summarize/__init__.py
dolphin_summarize/__main__.py
dolphin_summarize/cli.py
dolphin_summarize/core.py
dolphin_utils-0.4.2.dist-info/licenses/LICENSE
dolphin_utils-0.4.2.dist-info/METADATA
dolphin_utils-0.4.2.dist-info/WHEEL
dolphin_utils-0.4.2.dist-info/entry_points.txt
dolphin_utils-0.4.2.dist-info/top_level.txt
dolphin_utils-0.4.2.dist-info/RECORD
