Metadata-Version: 2.4
Name: dolphin-utils
Version: 0.4.2
Summary: Collection of utilities for AI/ML model analysis and processing
Author: Eric Hartford
License: MIT
Project-URL: Homepage, https://github.com/cognitivecomputations/dolphin-utils
Project-URL: Repository, https://github.com/cognitivecomputations/dolphin-utils
Project-URL: Issues, https://github.com/cognitivecomputations/dolphin-utils/issues
Keywords: machine-learning,model-analysis,safetensors,huggingface,architecture
Classifier: Development Status :: 4 - Beta
Classifier: Intended Audience :: Developers
Classifier: Intended Audience :: Science/Research
Classifier: License :: OSI Approved :: MIT License
Classifier: Operating System :: OS Independent
Classifier: Programming Language :: Python :: 3
Classifier: Programming Language :: Python :: 3.7
Classifier: Programming Language :: Python :: 3.8
Classifier: Programming Language :: Python :: 3.9
Classifier: Programming Language :: Python :: 3.10
Classifier: Programming Language :: Python :: 3.11
Classifier: Programming Language :: Python :: 3.12
Classifier: Topic :: Scientific/Engineering :: Artificial Intelligence
Classifier: Topic :: Software Development :: Libraries :: Python Modules
Requires-Python: >=3.6
License-File: LICENSE
Requires-Dist: huggingface_hub
Requires-Dist: requests
Requires-Dist: safetensors
Dynamic: license-file
Dynamic: requires-python
